DocumentTemplate/DT_HTML.py
DocumentTemplate/DT_If.py
DocumentTemplate/DT_In.py
DocumentTemplate/DT_InSV.py
DocumentTemplate/DT_Let.py
DocumentTemplate/DT_Raise.py
DocumentTemplate/DT_Return.py
DocumentTemplate/DT_String.py
DocumentTemplate/DT_Try.py
DocumentTemplate/DT_UI.py
DocumentTemplate/DT_Util.py
DocumentTemplate/DT_Var.py
DocumentTemplate/DT_With.py
DocumentTemplate/_DocumentTemplate.py
DocumentTemplate/__init__.py
DocumentTemplate/html_quote.py
DocumentTemplate/permissions.py
DocumentTemplate/security.py
DocumentTemplate/ustr.py
DocumentTemplate/sequence/__init__.py
DocumentTemplate/sequence/tests/__init__.py
DocumentTemplate/sequence/tests/results.py
DocumentTemplate/sequence/tests/testSequence.py
DocumentTemplate/sequence/tests/ztestlib.py
DocumentTemplate/tests/__init__.py
DocumentTemplate/tests/dealers.dtml
DocumentTemplate/tests/dealers.out
DocumentTemplate/tests/testDTML.py
DocumentTemplate/tests/testDTMLUnicode.py
DocumentTemplate/tests/testSecurity.py
DocumentTemplate/tests/test_DT_If.py
DocumentTemplate/tests/test_DT_In.py
DocumentTemplate/tests/test_DT_InSV.py
DocumentTemplate/tests/test_DT_Raise.py
DocumentTemplate/tests/test_DT_Try.py
DocumentTemplate/tests/test_DT_Var.py
DocumentTemplate/tests/test_DocumentTemplate.py
DocumentTemplate/tests/test_Util.py
DocumentTemplate/tests/test_permissions.py
DocumentTemplate/tests/test_templatedict.py
DocumentTemplate/tests/testustr.py
TreeDisplay/TreeTag.py
TreeDisplay/__init__.py
TreeDisplay/tests.py
documenttemplate-5.1.dist-info/licenses/LICENSE.txt
documenttemplate-5.1.dist-info/METADATA
documenttemplate-5.1.dist-info/WHEEL
documenttemplate-5.1.dist-info/top_level.txt
documenttemplate-5.1.dist-info/RECORD
