Metadata-Version: 2.4
Name: DocumentTemplate
Version: 5.1
Summary: Document Templating Markup Language (DTML)
Author-email: Zope Foundation and contributors <zope-dev@zope.dev>
Maintainer-email: Plone Foundation and contributors <zope-dev@zope.dev>
License-Expression: ZPL-2.1
Project-URL: Documentation, https://zope.readthedocs.io/en/latest/zopebook/index.html
Project-URL: Source, https://github.com/zopefoundation/DocumentTemplate
Project-URL: Issues, https://github.com/zopefoundation/DocumentTemplate/issues
Keywords: DTML,template,zope,HTML,SQL,web,markup
Classifier: Development Status :: 6 - Mature
Classifier: Environment :: Web Environment
Classifier: Framework :: Zope
Classifier: Framework :: Zope :: 5
Classifier: Operating System :: OS Independent
Classifier: Programming Language :: Python
Classifier: Programming Language :: Python :: 3
Classifier: Programming Language :: Python :: 3.10
Classifier: Programming Language :: Python :: 3.11
Classifier: Programming Language :: Python :: 3.12
Classifier: Programming Language :: Python :: 3.13
Classifier: Programming Language :: Python :: 3.14
Classifier: Programming Language :: Python :: Implementation :: CPython
Classifier: Topic :: Text Processing :: Markup
Requires-Python: >=3.10
License-File: LICENSE.txt
Requires-Dist: AccessControl>=4.0a5
Requires-Dist: Acquisition
Requires-Dist: ExtensionClass>=4.1a1
Requires-Dist: RestrictedPython>=4.0a1
Requires-Dist: roman
Requires-Dist: zExceptions
Requires-Dist: zope.sequencesort
Requires-Dist: zope.structuredtext
Provides-Extra: test
Requires-Dist: docutils; extra == "test"
Dynamic: license-file
